<?xml version="1.0" encoding="utf-8"?>
<XMLLevel xmlns:xsi="http://www.w3.org/2001/XMLSchema-instance" xmlns:xsd="http://www.w3.org/2001/XMLSchema" 
	monsterInputType="SoundLetter"
	CollectableMonster=""
	SegmentTime="11"
	HideCallout="-1"
	LettersGroup="1"
	StoneType="1"
>
  <Segments>
    <Segment spawnIds="63,64,17,94 ,29,33" SegmentTime="11">
    	<!-- Puzzle One -->
    	<MonsterRequiredLetters>
    		<string>ЗУБ</string>
    	</MonsterRequiredLetters>
    	<MonsterAllLetters>
    	</MonsterAllLetters>
    	<Stones>
    		<string>КУБ</string>
    		<string>КУБ</string>
			<string>ЗУБ</string>
			<string>ЗУБ</string>
			<string>КУБ</string>
			<string>ЗУБ</string>
    	</Stones>
	</Segment>
	<Segment spawnIds="64, 89, 92, 57, 28, 25, 56" SegmentTime="11">
		<!-- Puzzle Two -->
		<MonsterRequiredLetters>
			<string>ЧУМ</string>
		</MonsterRequiredLetters>
	  	<MonsterAllLetters>
	  	</MonsterAllLetters>
	  	<Stones>
        	<string>ДОМ</string>
        	<string>ЧУМ</string>
			<string>ЧУМ</string>
			<string>ДОМ</string>
			<string>ЧУМ</string>
			<string>ДОМ</string>
			<string bonusScore="100">FireWrongLetter</string>
      	</Stones>
    </Segment>
	<Segment spawnIds="64, 72, 25, 56, 73, 69, 63" SegmentTime="11">
		<!-- Puzzle Three -->
      	<MonsterRequiredLetters>
			<string>РЯД</string>
	  	</MonsterRequiredLetters>
	  	<MonsterAllLetters>
	  	</MonsterAllLetters>
	  	<Stones>
			<string>ДУБ</string>
	        <string>ДУБ</string>
			<string>ДУБ</string>
			<string>РЯД</string>
			<string>РЯД</string>
			<string>РЯД</string>
      	</Stones>
	</Segment>
	<Segment spawnIds="64, 72, 76, 57, 28, 69, 63" SegmentTime="11">
		<!-- Puzzle Four -->
      	<MonsterRequiredLetters>
			<string>ТАЗ</string>
	  	</MonsterRequiredLetters>
	  	<MonsterAllLetters>
	  	</MonsterAllLetters>
	  	<Stones>
	        <string>СОК</string>
	        <string>ТАЗ</string>
			<string>ТАЗ</string>
	        <string>ТАЗ</string>
			<string>СОК</string>
	        <string>СОК</string>
      	</Stones>
    </Segment>
	<Segment spawnIds="32,24,77,36,63,64,17" SegmentTime="11">
		<!-- Puzzle Five -->
      	<MonsterRequiredLetters>
			<string>ЧУБ</string>
	  	</MonsterRequiredLetters>
	  	<MonsterAllLetters>
	  	</MonsterAllLetters>
	  	<Stones>
			<string>ЧУБ</string>
	        <string>СОМ</string>
			<string>ЧУБ</string>
	        <string>СОМ</string>
			<string>СОМ</string>
	        <string>ЧУБ</string>
      	</Stones>
	</Segment>
  </Segments>
</XMLLevel>